dhon/__init__.py
dhon/args.py
dhon/core.py
dhon/main.py
dhon-0.0.14.data/scripts/dhon
dhon-0.0.14.dist-info/LICENSE
dhon-0.0.14.dist-info/METADATA
dhon-0.0.14.dist-info/WHEEL
dhon-0.0.14.dist-info/top_level.txt
dhon-0.0.14.dist-info/RECORD
