Metadata-Version: 2.1
Name: dhon
Version: 0.0.14
Summary: A small python package for currency conversion
Home-page: https://github.com/rusty-electron/dhon
Author: Pritom Gogoi
Author-email: pritomg@protonmail.com
Project-URL: Bug Tracker, https://github.com/rusty-electron/dhon/issues
Classifier: Programming Language :: Python :: 3
Classifier: License :: OSI Approved :: MIT License
Classifier: Operating System :: OS Independent
Requires-Python: >=3.6
License-File: LICENSE
Requires-Dist: requests
